MANIFEST.in
README.rst
setup.py
scanningegsinp/__init__.py
scanningegsinp/egsinp.py
scanningegsinp/options.toml
scanningegsinp/scanningegsinp.py
scanningegsinp/template.egsinp
scanningegsinp.egg-info/PKG-INFO
scanningegsinp.egg-info/SOURCES.txt
scanningegsinp.egg-info/dependency_links.txt
scanningegsinp.egg-info/entry_points.txt
scanningegsinp.egg-info/not-zip-safe
scanningegsinp.egg-info/requires.txt
scanningegsinp.egg-info/top_level.txt