Metadata-Version: 1.0
Name: scanningegsinp
Version: 0.2.4
Summary: Generate EGSINP files for a scanning target
Home-page: http://github.com/henrybaxter/scanningegsinp
Author: Henry Baxter
Author-email: henry.baxter@gmail.com
License: MIT
Platform: UNKNOWN
